Metadata-Version: 2.2
Name: coloring_package_for_py
Version: 0.1
Summary: A simple Python package for applying ANSI color codes and text effects in terminal output.
Home-page: https://github.com/K1ngbobb/coloring_package_for_py
Author: Kingbob
Author-email: business5kingbob@gmail.com
Classifier: Programming Language :: Python :: 3
Classifier: License :: OSI Approved :: MIT License
Classifier: Operating System :: OS Independent
Requires-Python: >=3.6
Dynamic: author
Dynamic: author-email
Dynamic: classifier
Dynamic: description
Dynamic: description-content-type
Dynamic: home-page
Dynamic: requires-python
Dynamic: summary
